optimizer4OS/__init__.py
optimizer4OS/cleaner/__init__.py
optimizer4OS/cleaner/base.py
optimizer4OS/cleaner/factor.py
optimizer4OS/cleaner/platform_cleaner.py
optimizer4OS-0.1.1.dist-info/METADATA
optimizer4OS-0.1.1.dist-info/WHEEL
optimizer4OS-0.1.1.dist-info/top_level.txt
optimizer4OS-0.1.1.dist-info/RECORD
