Metadata-Version: 2.1
Name: optimizer4OS
Version: 0.1.1
Summary: Cross-platform optimizer system cleaner library
Home-page: https://github.com/zhangwusan/optimizer
Author: Zhang Wusan
Author-email: zhangwusan1@gmail.com
Classifier: Programming Language :: Python :: 3
Classifier: License :: OSI Approved :: MIT License
Classifier: Operating System :: OS Independent
Requires-Python: >=3.6
